cfm_task_models/__init__.py
cfm_task_models/all_mim_download_mmseg_configs.py
cfm_task_models/dataset_download.py
cfm_task_models/legacy/__init__.py
cfm_task_models/legacy/assigners.py
cfm_task_models/legacy/builder_legacy.py
cfm_task_models/legacy/condconv.py
cfm_task_models/legacy/heads.py
cfm_task_models/legacy/loaders.py
cfm_task_models/legacy/losses.py
cfm_task_models/legacy/mmdet_extras.py
cfm_task_models/legacy/reppoints.py
cfm_task_models/legacy/utils.py
cfm_task_models/miminstaller.py
cfm_task_models/models/Swin-Transformer/CODE_OF_CONDUCT.md
cfm_task_models/models/Swin-Transformer/LICENSE
cfm_task_models/models/Swin-Transformer/MODELHUB.md
cfm_task_models/models/Swin-Transformer/README.md
cfm_task_models/models/Swin-Transformer/SECURITY.md
cfm_task_models/models/Swin-Transformer/SUPPORT.md
cfm_task_models/models/Swin-Transformer/__init__.py
cfm_task_models/models/Swin-Transformer/config.py
cfm_task_models/models/Swin-Transformer/configs/simmim/simmim_finetune__swin_base__img224_window7__800ep.yaml
cfm_task_models/models/Swin-Transformer/configs/simmim/simmim_finetune__swinv2_base__img224_window14__800ep.yaml
cfm_task_models/models/Swin-Transformer/configs/simmim/simmim_pretrain__swin_base__img192_window6__800ep.yaml
cfm_task_models/models/Swin-Transformer/configs/simmim/simmim_pretrain__swinv2_base__img192_window12__800ep.yaml
cfm_task_models/models/Swin-Transformer/configs/swin/swin_base_patch4_window12_384_22kto1k_finetune.yaml
cfm_task_models/models/Swin-Transformer/configs/swin/swin_base_patch4_window12_384_finetune.yaml
cfm_task_models/models/Swin-Transformer/configs/swin/swin_base_patch4_window7_224.yaml
cfm_task_models/models/Swin-Transformer/configs/swin/swin_base_patch4_window7_224_22k.yaml
cfm_task_models/models/Swin-Transformer/configs/swin/swin_base_patch4_window7_224_22kto1k_finetune.yaml
cfm_task_models/models/Swin-Transformer/configs/swin/swin_large_patch4_window12_384_22kto1k_finetune.yaml
cfm_task_models-0.1.0.dist-info/METADATA
cfm_task_models-0.1.0.dist-info/WHEEL
cfm_task_models-0.1.0.dist-info/entry_points.txt
cfm_task_models-0.1.0.dist-info/RECORD
